{
  "samples": [
    {
      "id": "CORE-001",
      "project": "东岭铜矿薄片",
      "borehole": "ZK-17",
      "coreBox": "BX-09",
      "depth": "128.4-128.8m",
      "owner": "陆川",
      "status": "制片中",
      "delivery": "未交付",
      "slices": [
        {
          "id": "SL-001-A",
          "method": "茜素红染色",
          "observation": "",
          "status": "研磨",
          "logs": [
            {
              "at": "2026-06-12T10:00:00.000Z",
              "step": "取样",
              "note": "截取含矿化条带位置"
            },
            {
              "at": "2026-06-13T11:20:00.000Z",
              "step": "切割",
              "note": "完成粗切"
            }
          ]
        }
      ]
    }
  ]
}